{
  "id": "fdf9f190-b234-452b-bf56-f18f06e1aadd",
  "uid": "voluptas-minima-officia",
  "type": "dynamic-page",
  "data": {
    "pageTitle": "generate frictionless deliverables",
    "seoTitle": "disintermediate bricks-and-clicks platforms",
    "seoDescription": "synergize viral methodologies",
    "seoImage": {
      "dimensions": {
        "width": 1200,
        "height": 630
      },
      "alt": "Placeholder image",
      "copyright": null,
      "url": "https://images.unsplash.com/photo-1571126770897-2d612d1f7b89?w=1200&h=630&fit=crop"
    }
  }
}