{
  "id": "address",
  "type": "SharedSlice",
  "name": "Address",
  "description": "Address",
  "variations": [
    {
      "id": "default-slice",
      "name": "Default slice",
      "docURL": "...",
      "version": "sktwi1xtmkfgx8626",
      "description": "Address",
      "primary": {
        "title": {
          "type": "StructuredText",
          "config": {
            "label": "Title",
            "placeholder": "This is where it all begins...",
            "allowTargetBlank": true,
            "single": "heading2"
          }
        },
        "address": {
          "config": {
            "label": "Address",
            "placeholder": "",
            "allowTargetBlank": false,
            "multi": "paragraph,strong"
          },
          "type": "StructuredText"
        }
      },
      "items": {}
    }
  ]
}