[
  {
    "__TYPE__": "SharedSliceContent",
    "variation": "default-slice",
    "primary": {
      "title": {
        "__TYPE__": "StructuredTextContent",
        "value": [
          {
            "type": "heading2",
            "content": {
              "text": "Close"
            }
          }
        ]
      }
    },
    "items": [
      {
        "__TYPE__": "GroupItemContent",
        "value": [
          [
            "subtitle",
            {
              "__TYPE__": "StructuredTextContent",
              "value": [
                {
                  "type": "heading3",
                  "content": {
                    "text": "Sudden"
                  }
                }
              ]
            }
          ],
          [
            "description",
            {
              "__TYPE__": "StructuredTextContent",
              "value": [
                {
                  "type": "paragraph",
                  "content": {
                    "text": "Duis ipsum incididunt ex incididunt enim. Sit magna ut nulla sit esse in dolor."
                  }
                }
              ]
            }
          ]
        ]
      }
    ]
  }
]